Metadata-Version: 2.1
Name: televisor
Version: 0.0.1
Summary: A tool for sending videos to telegram chats
Home-page: https://github.com/zeionara/televisor
Author: Zeio Nara
Author-email: zeionara@gmail.com
License: Apache 2.0
Project-URL: Documentation, https://github.com/zeionara/televisor#readme
Project-URL: Bug Reports, https://github.com/zeionara/televisor/issues
Project-URL: Source Code, https://github.com/zeionara/televisor
Classifier: Intended Audience :: Developers
Classifier: License :: OSI Approved :: Apache Software License
Classifier: Programming Language :: Python :: 3.12
License-File: LICENSE
Requires-Dist: click
Requires-Dist: python-telegram-bot
